{"dependencies":[{"name":"./css/fontawesome-all.min.css","dynamic":true},{"name":"./css/style.css","dynamic":true},{"name":"./js/Node.js","dynamic":true},{"name":"./js/Nested.js","dynamic":true},{"name":"./js/app.js","dynamic":true}],"generated":{"html":"<!DOCTYPE html>\n<html lang=\"fr\">\n<head>\n    <meta charset=\"UTF-8\">\n    <meta name=\"viewport\" content=\"width=device-width, initial-scale=1.0\">\n    <meta http-equiv=\"X-UA-Compatible\" content=\"ie=edge\">\n    <title>Nested</title>\n    <link rel=\"stylesheet\" href=\"public/dist/6e0c36ecb4c08e0a0bf06c1f70a96af8.css\">\n    <link rel=\"stylesheet\" href=\"public/dist/d9db8f662958378313ced0481a9d123a.css\">\n</head>\n<body>\n    <div class=\"container\">\n        <nav id=\"breadcrumb\" class=\"breadcrumb\"></nav>\n        <aside id=\"tree\" class=\"tree\"></aside>\n        <article id=\"mainframe\" class=\"mainframe\">\n            <section id=\"mainframe-list\" class=\"mainframe-list\"></section>\n            <section id=\"mainframe-details\" class=\"mainframe-details\"></section>\n        </article>\n    </div>\n\n    <script src=\"public/dist/a1115572471180a970d4d1646392bccf.js\"></script>\n    <script src=\"public/dist/2a21fa791b7827ab79e55e30357d2b10.js\"></script>\n    <script src=\"public/dist/323828e0830b734524f319dcb44e2407.js\"></script>\n</body>\n</html>"},"hash":"91190f171a49495d5c6289747dd73f17","cacheData":{}}